ipyvolume/__init__.py
ipyvolume/_version.py
ipyvolume/astro.py
ipyvolume/bokeh.py
ipyvolume/datasets.py
ipyvolume/embed.py
ipyvolume/examples.py
ipyvolume/headless.py
ipyvolume/hotreload.py
ipyvolume/moviemaker.py
ipyvolume/pylab.py
ipyvolume/serialize.py
ipyvolume/styles.py
ipyvolume/test_all.py
ipyvolume/traittypes.py
ipyvolume/transferfunction.py
ipyvolume/ui.py
ipyvolume/utils.py
ipyvolume/widgets.py
ipyvolume/vue/container.vue
ipyvolume/vue/legend.vue
ipyvolume/vue/popup.vue
ipyvolume-0.6.3.data/data/etc/jupyter/nbconfig/notebook.d/ipyvolume.json
ipyvolume-0.6.3.data/data/share/jupyter/labextensions/ipyvolume/package.json
ipyvolume-0.6.3.data/data/share/jupyter/labextensions/ipyvolume/static/212.b0149a14735c9b14c049.js
ipyvolume-0.6.3.data/data/share/jupyter/labextensions/ipyvolume/static/212.b0149a14735c9b14c049.js.LICENSE.txt
ipyvolume-0.6.3.data/data/share/jupyter/labextensions/ipyvolume/static/261.a9c9630b28934bcbf1c3.js
ipyvolume-0.6.3.data/data/share/jupyter/labextensions/ipyvolume/static/466.df53a5241872f78b6b60.js
ipyvolume-0.6.3.data/data/share/jupyter/labextensions/ipyvolume/static/466.df53a5241872f78b6b60.js.LICENSE.txt
ipyvolume-0.6.3.data/data/share/jupyter/labextensions/ipyvolume/static/486.59ac5542d87a8f7709e9.js
ipyvolume-0.6.3.data/data/share/jupyter/labextensions/ipyvolume/static/486.59ac5542d87a8f7709e9.js.LICENSE.txt
ipyvolume-0.6.3.data/data/share/jupyter/labextensions/ipyvolume/static/501.54c2baeab80ecb56ca08.js
ipyvolume-0.6.3.data/data/share/jupyter/labextensions/ipyvolume/static/568.df354347cf6898d012c4.js
ipyvolume-0.6.3.data/data/share/jupyter/labextensions/ipyvolume/static/577.ef610ec4539ffe9cddc1.js
ipyvolume-0.6.3.data/data/share/jupyter/labextensions/ipyvolume/static/577.ef610ec4539ffe9cddc1.js.LICENSE.txt
ipyvolume-0.6.3.data/data/share/jupyter/labextensions/ipyvolume/static/58.5dd767d4301576cee659.js
ipyvolume-0.6.3.data/data/share/jupyter/labextensions/ipyvolume/static/64.e6b27f39dcb5e033dca2.js
ipyvolume-0.6.3.dist-info/LICENSE
ipyvolume-0.6.3.dist-info/METADATA
ipyvolume-0.6.3.dist-info/WHEEL
ipyvolume-0.6.3.dist-info/top_level.txt
ipyvolume-0.6.3.dist-info/RECORD
