Metadata-Version: 2.1
Name: ipyvolume
Version: 0.6.3
Summary: IPython widget for rendering 3d volumes
Home-page: https://github.com/maartenbreddels/ipyvolume
Author: Maarten A. Breddels
Author-email: maartenbreddels@gmail.com
License: MIT
Keywords: ipython,jupyter,widgets,volume rendering
Classifier: Development Status :: 4 - Beta
Classifier: Framework :: IPython
Classifier: Intended Audience :: Developers
Classifier: Intended Audience :: Science/Research
Classifier: Topic :: Multimedia :: Graphics
Classifier: Programming Language :: Python :: 3
Classifier: Programming Language :: Python :: 3.6
Classifier: Programming Language :: Python :: 3.7
Classifier: Programming Language :: Python :: 3.8
License-File: LICENSE
